_spyder.cpython-38-darwin.so
spyder/__init__.py
spyder/der.py
spy_der-0.4.1.dist-info/LICENSE
spy_der-0.4.1.dist-info/METADATA
spy_der-0.4.1.dist-info/WHEEL
spy_der-0.4.1.dist-info/entry_points.txt
spy_der-0.4.1.dist-info/top_level.txt
spy_der-0.4.1.dist-info/RECORD
