Metadata-Version: 2.1
Name: spy-der
Version: 0.4.1
Summary: A simple Python package for fast DER computation
Home-page: https://github.com/desh2608/spyder
Author: Desh Raj
Author-email: r.desh26@gmail.com
License-File: LICENSE
Requires-Dist: click (>=7.0.0)
Requires-Dist: tabulate (>=0.8.9)
Requires-Dist: numpy (>=1.18.1)
Provides-Extra: all
Requires-Dist: click (>=7.0.0) ; extra == 'all'
Requires-Dist: tabulate (>=0.8.9) ; extra == 'all'
Requires-Dist: numpy (>=1.18.1) ; extra == 'all'
Requires-Dist: pytest (==7.1.3) ; extra == 'all'
Requires-Dist: pytest-forked (==1.4.0) ; extra == 'all'
Requires-Dist: pytest-xdist (==2.5.0) ; extra == 'all'
Requires-Dist: pytest-cov (==4.0.0) ; extra == 'all'
Requires-Dist: flake8 (==5.0.4) ; extra == 'all'
Requires-Dist: coverage (==6.5.0) ; extra == 'all'
Requires-Dist: black (==22.3.0) ; extra == 'all'
Requires-Dist: isort (==5.10.1) ; extra == 'all'
Requires-Dist: pre-commit (<=2.19.0,>=2.17.0) ; extra == 'all'
Provides-Extra: tests
Requires-Dist: pytest (==7.1.3) ; extra == 'tests'
Requires-Dist: pytest-forked (==1.4.0) ; extra == 'tests'
Requires-Dist: pytest-xdist (==2.5.0) ; extra == 'tests'
Requires-Dist: pytest-cov (==4.0.0) ; extra == 'tests'
Requires-Dist: flake8 (==5.0.4) ; extra == 'tests'
Requires-Dist: coverage (==6.5.0) ; extra == 'tests'
Requires-Dist: black (==22.3.0) ; extra == 'tests'
Requires-Dist: isort (==5.10.1) ; extra == 'tests'
Requires-Dist: pre-commit (<=2.19.0,>=2.17.0) ; extra == 'tests'
